<BackupInst xmlns="http://www.microsoft.com/GroupPolicy/GPOOperations/Manifest"><GPOGuid><![CDATA[{C70E3C7C-FF21-4CCD-81A1-B4D43A04632E}]]></GPOGuid><GPODomain><![CDATA[windomain.local]]></GPODomain><GPODomainGuid><![CDATA[{0c573455-e6da-4e47-a954-7bc2f1adc7e5}]]></GPODomainGuid><GPODomainController><![CDATA[dc.windomain.local]]></GPODomainController><BackupTime><![CDATA[2017-04-12T03:58:34]]></BackupTime><ID><![CDATA[{8F52D06C-5877-4D18-979F-6AB3C98A32F7}]]></ID><Comment><![CDATA[]]></Comment><GPODisplayName><![CDATA[Windows Event Forwarding Server]]></GPODisplayName></BackupInst>
